zaiclient/__init__.py
zaiclient/__main__.py
zaiclient/auth.py
zaiclient/client.py
zaiclient/config.py
zaiclient/exceptions/BatchSizeLimitExceededException.py
zaiclient/exceptions/EmptyBatchException.py
zaiclient/exceptions/InputLengthNotEqualException.py
zaiclient/exceptions/InputTypeNotEqualException.py
zaiclient/exceptions/ZaiClientException.py
zaiclient/exceptions/__init__.py
zaiclient/http.py
zaiclient/request/Events/AddCartaddEvent.py
zaiclient/request/Events/AddCustomEvent.py
zaiclient/request/Events/AddLikeEvent.py
zaiclient/request/Events/AddPageViewEvent.py
zaiclient/request/Events/AddProductDetailViewEvent.py
zaiclient/request/Events/AddPurchaseEvent.py
zaiclient/request/Events/AddRateEvent.py
zaiclient/request/Events/AddSearchEvent.py
zaiclient/request/Events/Event.py
zaiclient/request/Events/EventRequest.py
zaiclient/request/Events/__init__.py
zaiclient/request/Items/AddItem.py
zaiclient/request/Items/DeleteItem.py
zaiclient/request/Items/Item.py
zaiclient/request/Items/ItemRequest.py
zaiclient/request/Items/UpdateItem.py
zaiclient/request/Items/__init__.py
zaiclient/request/Recommendations/GetCustomRecommendation.py
zaiclient/request/Recommendations/GetRelatedItemsRecommendation.py
zaiclient/request/Recommendations/GetRerankingRecommendation.py
zaiclient/request/Recommendations/GetUserRecommendation.py
zaiclient/request/Recommendations/Recommendation.py
zaiclient/request/Recommendations/RecommendationRequest.py
zaiclient/request/Recommendations/__init__.py
zaiclient/request/Request.py
zaiclient/request/__init__.py
zaiclient/response/EventLoggerResponse.py
zaiclient/response/ItemResponse.py
zaiclient/response/RecommendationResponse.py
zaiclient/response/__init__.py
zaiclient-4.3.1.dist-info/METADATA
zaiclient-4.3.1.dist-info/WHEEL
zaiclient-4.3.1.dist-info/RECORD
