Metadata-Version: 2.1
Name: zaiclient
Version: 4.3.1
Summary: Z.Ai official client SDK.
Home-page: https://github.com/zaikorea/zaiclient-python
License: Proprietary
Author: Z.Ai Inc.
Author-email: tech@zaikorea.org
Requires-Python: >=3.7,<4.0
Classifier: Intended Audience :: Developers
Classifier: Intended Audience :: Science/Research
Classifier: License :: Other/Proprietary License
Classifier: Programming Language :: Python :: 3
Classifier: Programming Language :: Python :: 3.7
Classifier: Programming Language :: Python :: 3.8
Classifier: Programming Language :: Python :: 3.9
Classifier: Programming Language :: Python :: 3.10
Classifier: Programming Language :: Python :: 3.11
Classifier: Programming Language :: Python :: 3.12
Classifier: Programming Language :: Python :: 3.6
Classifier: Topic :: Scientific/Engineering
Classifier: Topic :: Scientific/Engineering :: Artificial Intelligence
Classifier: Topic :: Software Development
Classifier: Topic :: Software Development :: Libraries
Classifier: Topic :: Software Development :: Libraries :: Python Modules
Requires-Dist: pydantic (>=1.7.2,<2.0.0) ; python_version < "3.7"
Requires-Dist: pydantic (>=1.9.0,<2.0.0) ; python_version >= "3.7"
Requires-Dist: requests (>=2.26.0,<3.0.0)
